alpaca_daily_losers/__init__.py
alpaca_daily_losers/close_positions.py
alpaca_daily_losers/daily_losers.py
alpaca_daily_losers/global_functions.py
alpaca_daily_losers/liquidate.py
alpaca_daily_losers/openai.py
alpaca_daily_losers/slack.py
alpaca_daily_losers/statistics.py
py_alpaca_daily_losers-2.2.8.dist-info/METADATA
py_alpaca_daily_losers-2.2.8.dist-info/WHEEL
py_alpaca_daily_losers-2.2.8.dist-info/RECORD
