Metadata-Version: 2.1
Name: py-alpaca-daily-losers
Version: 2.2.8
Summary: Daily Losers strategy, uses py-alpaca-api for Alpaca Markets integration.
Home-page: https://pypi.org/project/py-alpaca-daily-losers/
License: MIT
Author: TexasCoding
Author-email: jeff10278@me.com
Requires-Python: >=3.12,<4.0
Classifier: License :: OSI Approved :: MIT License
Classifier: Programming Language :: Python :: 3
Classifier: Programming Language :: Python :: 3.12
Requires-Dist: numpy (>=1.26,<2.0)
Requires-Dist: openai (>=1.30.5,<2.0.0)
Requires-Dist: py-alpaca-api (>=2.0.0,<3.0.0)
Requires-Dist: requests (>=2.32.3,<3.0.0)
Requires-Dist: slack-sdk (>=3.27.2,<4.0.0)
Requires-Dist: ta (>=0.11.0,<0.12.0)
Requires-Dist: tenacity (>=8.4.1,<9.0.0)
Project-URL: Documentation, https://py-alpaca-daily-losers.readthedocs.io/en/latest/
Project-URL: Repository, https://github.com/TexasCoding/py-alpaca-daily-losers
